egosms_sdk/__init__.py
egosms_sdk/v1/__init__.py
egosms_sdk/v1/egosms_sdk.py
egosms_sdk/v1/models.py
egosms_sdk/v1/utils.py
egosms_sdk-1.0.0.dist-info/METADATA
egosms_sdk-1.0.0.dist-info/WHEEL
egosms_sdk-1.0.0.dist-info/top_level.txt
egosms_sdk-1.0.0.dist-info/RECORD
