Metadata-Version: 2.4
Name: egosms_sdk
Version: 1.0.0
Summary: EgoSMS Python SDK
Author-email: Pahappa Limited <systems@pahappa.com>
License: MIT
Requires-Dist: requests
